{"0": "stori", "1": "sickli", "2": "clan", "3": "who", "4": "poetri", "5": "consort", "6": "famili", "7": "share", "8": "a", "9": "exemplifi", "10": "visit", "11": "exist", "12": "mend", "13": "from", "14": "to", "15": "world", "16": "most", "17": "''", "18": "mansion", "19": "carefre", "20": "provid", "21": "influenc", "22": "stone", "23": "special", "24": "intellig", "25": "friendship", "26": "romant", "27": "aristocrat", "28": "piec", "29": "emot", "30": "wa", "31": "royal", "32": "wealthi", "33": "buddhist", "34": "adjac", "35": "were", "36": "see", "37": "hundr", "38": "frame", "39": "with", "40": "\u2019", "41": "born", "42": "when", "43": "cousin", "44": "marri", "45": "into", "46": "monk", "47": "connect", "48": "four", "49": "lush", "50": "merg", "51": "wealth", "52": "is", "53": "enter", "54": "aeon", "55": "citi", "56": "rivalri", "57": "ha", "58": ".", "59": "He", "60": "illustri", "61": "anoth", "62": "xue", "63": "lin", "64": "love", "65": "\u2014who", "66": "beg", "67": "are", "68": "whom", "69": "\u8cc8", "70": "prestig", "71": "her", "72": "jade", "73": "chanc", "74": "fortun", "75": "disfavor", "76": "priest", "77": "emperor", "78": "they", "79": "woman", "80": "but", "81": "backdrop", "82": "some", "83": "garden", "84": "by", "85": "bring", "86": "eventu", "87": "\u5be7\u570b\u5e9c", "88": "abandon", "89": "mouth", "90": "minor", "91": "ningguo", "92": "height", "93": "music", "94": "magic", "95": "their", "96": "heir", "97": "s", "98": "larg", "99": "mortal", "100": "jia", "101": "built", "102": "baoyu", "103": "human", "104": "charact", "105": "companion", "106": "an", "107": "along", "108": "(", "109": "one", "110": "grace", "111": "two", "112": "offspr", "113": "among", "114": "heaven", "115": "thirti", "116": "``", "117": "baochai", "118": "great", "119": "whose", "120": "resid", "121": "hous", "122": "same", "123": "over", "124": "in", "125": "describ", "126": "realm", "127": "them", "128": "compound", "129": "male", "130": "sentient", "131": "capit", "132": "hi", "133": "it", "134": "ancestor", "135": ")", "136": "thi", "137": "life", "138": "goddess", "139": "clan\u2014th", "140": "three", "141": "rongguo", "142": "detail", "143": "made", "144": "follow", "145": "and", "146": "taoist", "147": "howev", "148": "\u69ae\u570b\u5e9c", "149": "receiv", "150": "confisc", "151": "record", "152": "daiyu", "153": "duke", "154": "of", "155": ",", "156": "titl", "157": "landscap", "158": "naturalist", "159": "raid", "160": "imperi", "161": "she", "162": "as", "163": "'s", "164": "fall", "165": "chart", "166": "predestin", "167": "episod", "168": "adolesc", "169": "then", "170": "main", "171": "In", "172": "bond", "173": "he", "174": "novel", "175": "the", "176": "cheng-gao", "177": "ago", "178": "n\u00fcwa", "179": "version", "180": "branch", "181": "given", "182": "lack", "183": "begin", "184": "learn", "185": "against", "186": "ideal", "187": "form", "188": "declin"}